HtmlRumenjiaochengCYuyanBianchengWang/README.md
HtmlRumenjiaochengCYuyanBianchengWang/__init__.py
HtmlRumenjiaochengCYuyanBianchengWang/__main__.py
HtmlRumenjiaochengCYuyanBianchengWang/file.epub
HtmlRumenjiaochengCYuyanBianchengWang/index.html
HtmlRumenjiaochengCYuyanBianchengWang/css/__init__.py
HtmlRumenjiaochengCYuyanBianchengWang/css/annotations.css
HtmlRumenjiaochengCYuyanBianchengWang/css/main.css
HtmlRumenjiaochengCYuyanBianchengWang/css/normalize.css
HtmlRumenjiaochengCYuyanBianchengWang/css/popup.css
HtmlRumenjiaochengCYuyanBianchengWang/font/__init__.py
HtmlRumenjiaochengCYuyanBianchengWang/font/fontello.eot
HtmlRumenjiaochengCYuyanBianchengWang/font/fontello.svg
HtmlRumenjiaochengCYuyanBianchengWang/font/fontello.ttf
HtmlRumenjiaochengCYuyanBianchengWang/font/fontello.woff
HtmlRumenjiaochengCYuyanBianchengWang/img/__init__.py
HtmlRumenjiaochengCYuyanBianchengWang/img/annotator-glyph-sprite.png
HtmlRumenjiaochengCYuyanBianchengWang/img/annotator-icon-sprite.png
HtmlRumenjiaochengCYuyanBianchengWang/img/apple-touch-icon.png
HtmlRumenjiaochengCYuyanBianchengWang/img/cancelfullscreen.png
HtmlRumenjiaochengCYuyanBianchengWang/img/close.png
HtmlRumenjiaochengCYuyanBianchengWang/img/fullscreen.png
HtmlRumenjiaochengCYuyanBianchengWang/img/loader.gif
HtmlRumenjiaochengCYuyanBianchengWang/img/menu-icon.png
HtmlRumenjiaochengCYuyanBianchengWang/img/save.png
HtmlRumenjiaochengCYuyanBianchengWang/img/saved.png
HtmlRumenjiaochengCYuyanBianchengWang/img/settings-s.png
HtmlRumenjiaochengCYuyanBianchengWang/img/settings.png
HtmlRumenjiaochengCYuyanBianchengWang/img/star.png
HtmlRumenjiaochengCYuyanBianchengWang/js/__init__.py
HtmlRumenjiaochengCYuyanBianchengWang/js/epub.js
HtmlRumenjiaochengCYuyanBianchengWang/js/epub.min.js
HtmlRumenjiaochengCYuyanBianchengWang/js/epub.min.map
HtmlRumenjiaochengCYuyanBianchengWang/js/hooks.min.js
HtmlRumenjiaochengCYuyanBianchengWang/js/hooks.min.map
HtmlRumenjiaochengCYuyanBianchengWang/js/reader.js
html_rumenjiaocheng_c_yuyan_biancheng_wang-2024.3.4.0.dist-info/METADATA
html_rumenjiaocheng_c_yuyan_biancheng_wang-2024.3.4.0.dist-info/WHEEL
html_rumenjiaocheng_c_yuyan_biancheng_wang-2024.3.4.0.dist-info/entry_points.txt
html_rumenjiaocheng_c_yuyan_biancheng_wang-2024.3.4.0.dist-info/top_level.txt
html_rumenjiaocheng_c_yuyan_biancheng_wang-2024.3.4.0.dist-info/RECORD
